oxr/__init__.py
oxr/_base.py
oxr/_exceptions.py
oxr/_types.py
oxr/client.py
oxr/conftest.py
oxr/exceptions.py
oxr/py.typed
oxr/responses.py
oxr/asynchronous/__init__.py
oxr/asynchronous/client.py
oxr/asynchronous/tests/__init__.py
oxr/asynchronous/tests/test_client.py
oxr/asynchronous/tests/test_integration.py
oxr/tests/__init__.py
oxr/tests/test_client.py
oxr/tests/test_integration.py
oxr-0.1.1.dist-info/METADATA
oxr-0.1.1.dist-info/WHEEL
oxr-0.1.1.dist-info/licenses/LICENSE
oxr-0.1.1.dist-info/RECORD
