Metadata-Version: 2.3
Name: oxr
Version: 0.1.1
Summary: Type-safe client for the openexchangerates API.
Author-email: Maxwell Muoto <maxmuoto@gmail.com>
License: MIT License
Requires-Python: >=3.9
Requires-Dist: pydantic<3,>=2.0.0
Requires-Dist: requests<3,>=2.0.0
Requires-Dist: typing-extensions<5,>=4.0.0
Provides-Extra: async
Requires-Dist: aiohttp<4,>=3.0.0; extra == 'async'
